tensorflow_io/__init__.py
tensorflow_io/arrow.py
tensorflow_io/bigquery.py
tensorflow_io/kafka.py
tensorflow_io/core/__init__.py
tensorflow_io/core/grpc/__init__.py
tensorflow_io/python/__init__.py
tensorflow_io/python/api/__init__.py
tensorflow_io/python/api/audio.py
tensorflow_io/python/api/bigtable.py
tensorflow_io/python/api/genome.py
tensorflow_io/python/api/image.py
tensorflow_io/python/api/version.py
tensorflow_io/python/api/experimental/__init__.py
tensorflow_io/python/api/experimental/color.py
tensorflow_io/python/api/experimental/columnar.py
tensorflow_io/python/api/experimental/elasticsearch.py
tensorflow_io/python/api/experimental/ffmpeg.py
tensorflow_io/python/api/experimental/filesystem.py
tensorflow_io/python/api/experimental/filter.py
tensorflow_io/python/api/experimental/image.py
tensorflow_io/python/api/experimental/mongodb.py
tensorflow_io/python/api/experimental/serialization.py
tensorflow_io/python/api/experimental/streaming.py
tensorflow_io/python/api/experimental/text.py
tensorflow_io/python/experimental/__init__.py
tensorflow_io/python/experimental/avro_record_dataset_ops.py
tensorflow_io/python/experimental/color_ops.py
tensorflow_io/python/experimental/elasticsearch_dataset_ops.py
tensorflow_io/python/experimental/ffmpeg_ops.py
tensorflow_io/python/experimental/file_dataset_ops.py
tensorflow_io/python/experimental/filesystem_ops.py
tensorflow_io/python/experimental/filter_ops.py
tensorflow_io/python/experimental/grpc_dataset_ops.py
tensorflow_io/python/experimental/grpc_endpoint.py
tensorflow_io/python/experimental/image_dataset_ops.py
tensorflow_io/python/experimental/image_ops.py
tensorflow_io/python/experimental/io_dataset_ops.py
tensorflow_io/python/experimental/io_layer.py
tensorflow_io/python/experimental/io_tensor.py
tensorflow_io/python/experimental/kafka_batch_io_dataset_ops.py
tensorflow_io/python/experimental/kafka_group_io_dataset_ops.py
tensorflow_io/python/experimental/kafka_io_layer_ops.py
tensorflow_io-0.37.1.dist-info/LICENSE
tensorflow_io-0.37.1.dist-info/METADATA
tensorflow_io-0.37.1.dist-info/WHEEL
tensorflow_io-0.37.1.dist-info/top_level.txt
tensorflow_io-0.37.1.dist-info/RECORD
