Metadata-Version: 2.1
Name: tensorflow-io
Version: 0.37.1
Summary: TensorFlow IO
Home-page: https://github.com/tensorflow/io
Author: Google Inc.
Author-email: opensource@google.com
License: UNKNOWN
Download-URL: https://github.com/tensorflow/io/tags
Project-URL: Source, https://github.com/tensorflow/io
Project-URL: Bug Reports, https://github.com/tensorflow/io/issues
Project-URL: Documentation, https://tensorflow.org/io
Keywords: tensorflow io machine learning
Platform: UNKNOWN
Classifier: Development Status :: 4 - Beta
Classifier: Intended Audience :: Developers
Classifier: Intended Audience :: Education
Classifier: Intended Audience :: Science/Research
Classifier: License :: OSI Approved :: Apache Software License
Classifier: Programming Language :: Python :: 3
Classifier: Programming Language :: Python :: 3.7
Classifier: Programming Language :: Python :: 3.8
Classifier: Programming Language :: Python :: 3.9
Classifier: Programming Language :: Python :: 3.10
Classifier: Programming Language :: Python :: 3.11
Classifier: Programming Language :: Python :: 3.12
Classifier: Programming Language :: Python :: 3 :: Only
Classifier: Topic :: Scientific/Engineering
Classifier: Topic :: Scientific/Engineering :: Mathematics
Classifier: Topic :: Scientific/Engineering :: Artificial Intelligence
Classifier: Topic :: Software Development
Classifier: Topic :: Software Development :: Libraries
Classifier: Topic :: Software Development :: Libraries :: Python Modules
Requires-Python: >=3.7, <3.13
License-File: LICENSE
Requires-Dist: tensorflow-io-gcs-filesystem ==0.37.1
Provides-Extra: tensorflow
Requires-Dist: tensorflow <2.17.0,>=2.16.0 ; extra == 'tensorflow'
Provides-Extra: tensorflow-aarch64
Requires-Dist: tensorflow-aarch64 <2.17.0,>=2.16.0 ; extra == 'tensorflow-aarch64'
Provides-Extra: tensorflow-cpu
Requires-Dist: tensorflow-cpu <2.17.0,>=2.16.0 ; extra == 'tensorflow-cpu'
Provides-Extra: tensorflow-gpu
Requires-Dist: tensorflow-gpu <2.17.0,>=2.16.0 ; extra == 'tensorflow-gpu'
Provides-Extra: tensorflow-rocm
Requires-Dist: tensorflow-rocm <2.17.0,>=2.16.0 ; extra == 'tensorflow-rocm'
